README.md
setup.cfg
setup.py
pysimporter/__init__.py
pysimporter.egg-info/PKG-INFO
pysimporter.egg-info/SOURCES.txt
pysimporter.egg-info/dependency_links.txt
pysimporter.egg-info/requires.txt
pysimporter.egg-info/top_level.txt
pysimporter/borys_helpers/__init__.py
pysimporter/borys_helpers/proxy_helper.py
pysimporter/downloader_helpers/__init__.py
pysimporter/downloader_helpers/downloader_helper.py
pysimporter/downloader_helpers/proxy_helper.py
pysimporter/downloader_helpers/user_agents.py
pysimporter/kupazavr_helpers/__init__.py
pysimporter/kupazavr_helpers/helpers.py
pysimporter/logferts_helpers/__init__.py
pysimporter/logferts_helpers/db_helper.py
pysimporter/logferts_helpers/log_helper.py